{
  "name": "Lula Reeves",
  "age": 53,
  "address": {
    "street": "Lukag Key",
    "city": "Azivolab",
    "state": "WV",
    "zip": "95205"
  },
  "contact": {
    "phone": "(659) 834-7274",
    "servicePhone": "800487339"
  },
  "birthday": "1975-10-20T04:20:59.146Z",
  "ip": "118.67.240.215",
  "foo": "bar",
  "profile": {
    "about": "Alafo wufi ce koca af zoctodik ufovekij cislodo ocoh li rusura na zamhat roved ap huubegi. Kawezar muvduh se wubre niw rod sikar ce wanen weedu jo ete. Aja muni boztap se si uva gaf lekezoc ehco om hujulci sadvipak utudor. Nifloj joruj umuw lognij tijror vusafu wut jesiktom fizifbaf wizgonpu nup vorogu kenez duwuru hazegdud don he. El numatar unamu les ojfu butmas po nevpesgev ejvolak tu lihwo alaape.",
    "bio": "Wasfahceg doc aka naozu hirrojov pun nujpe ewmi ti rej jinare bopef febefe. Tatappir munmaf gicenda si geojo ukeecsaf hiwajuce icenaruz huhisic ewelipup bow kag. Ogpiva eho tipev vududem sebfetaj gilfahepu na wu hanhelapi dan esnez fakzuc ola. Cu rijmuap moz dagmedori vir ikauh viji budpapnin ugi uhuifa nut kalsaoc. Go uwaobobe vod lin bo zecna us busebza mu tazkarbim lalov wavrerle dupolma ivimu."
  },
  "apiKey": "75e46595c291fca8d1922a7ca5e2dc0d09c007758a608b18de78ac94800567b2",
  "currency": {
    "code": "MUR",
    "name": "Mauritius Rupee"
  }
}